worldfactbook/__init__.py
worldfactbook/world_factbook.json
worldfactbook/worldfactbook.py
worldfactbook-0.1.3.dist-info/licenses/LICENSE
worldfactbook-0.1.3.dist-info/METADATA
worldfactbook-0.1.3.dist-info/WHEEL
worldfactbook-0.1.3.dist-info/top_level.txt
worldfactbook-0.1.3.dist-info/RECORD
