Metadata-Version: 2.4
Name: worldfactbook
Version: 0.1.3
Summary: A Python library for fetching and processing data from the CIA World Factbook.
Author-email: Laplace's Demon <contact@laplacesdemon.com>
License-Expression: MIT
Project-URL: Homepage, https://github.com/lapdem/worldfactbook
Project-URL: Repository, https://github.com/lapdem/worldfactbook
Requires-Python: >=3.8
License-File: LICENSE
Requires-Dist: requests
Dynamic: license-file
